tool.py
dirA/__init__.py
dirA/kunkun.py
dirA-1.0.1.dist-info/LICENSE.txt
dirA-1.0.1.dist-info/METADATA
dirA-1.0.1.dist-info/WHEEL
dirA-1.0.1.dist-info/top_level.txt
dirA-1.0.1.dist-info/RECORD
