Metadata-Version: 2.1
Name: dirA
Version: 1.0.1
Summary: test inside is kunkun
Author: xiaotiantian
Author-email: xiaotiantian@163.com
License: MIT
License-File: LICENSE.txt
